config.py
flask_mongo_db.py
tg_tools.py
tg_tools-0.0.7.dist-info/LICENSE.txt
tg_tools-0.0.7.dist-info/METADATA
tg_tools-0.0.7.dist-info/WHEEL
tg_tools-0.0.7.dist-info/top_level.txt
tg_tools-0.0.7.dist-info/RECORD
